typertype/__init__.py
typertype/main.py
typertype/src/__init__.py
typertype/src/general.py
typertype/src/list_of_words.txt
typertype/src/main.py
typertype/src/main_copy.py
typertype/src/quotes_mode.py
typertype/src/read_settings.py
typertype/src/time_mode.py
typertype/src/word_modification.py
typertype/src/words_mode.py
typertype-1.1.4.dist-info/LICENSE
typertype-1.1.4.dist-info/METADATA
typertype-1.1.4.dist-info/WHEEL
typertype-1.1.4.dist-info/top_level.txt
typertype-1.1.4.dist-info/RECORD
