Metadata-Version: 2.1
Name: typertype
Version: 1.1.4
Summary: An offline, customizable, feature-rich, typing app
Home-page: https://github.com/StephenXie/Typertype
Author: Stephen Xie
Author-email: xiepin225@gmail.com
License: GPLv3
Keywords: type,typing,offline,customizable
Platform: UNKNOWN
Classifier: Intended Audience :: Developers
Classifier: Programming Language :: Python :: 3
Classifier: License :: OSI Approved :: GNU General Public License v3 (GPLv3)
Classifier: Operating System :: OS Independent
Requires-Python: >=3.6
License-File: LICENSE
